mineru/__init__.py
mineru/api.py
mineru/cli.py
mineru/config.py
mineru/examples.py
mineru/language.py
mineru/server.py
mineru_mcp-1.0.0.dist-info/METADATA
mineru_mcp-1.0.0.dist-info/WHEEL
mineru_mcp-1.0.0.dist-info/entry_points.txt
mineru_mcp-1.0.0.dist-info/top_level.txt
mineru_mcp-1.0.0.dist-info/RECORD
