Metadata-Version: 2.4
Name: mineru-mcp
Version: 1.0.0
Summary: MinerU MCP Server for PDF to Markdown conversion
Author-email: minerU <OpenDataLab@pjlab.org.cn>
License: MIT
Classifier: Programming Language :: Python :: 3
Classifier: License :: OSI Approved :: MIT License
Classifier: Operating System :: OS Independent
Requires-Python: <4.0,>=3.10
Requires-Dist: fastmcp>=2.5.2
Requires-Dist: python-dotenv>=1.0.0
Requires-Dist: requests>=2.31.0
Requires-Dist: aiohttp>=3.9.0
Requires-Dist: httpx>=0.24.0
Requires-Dist: uvicorn>=0.20.0
Requires-Dist: starlette>=0.27.0
